FlottaAuto/__init__.py
FlottaAuto/flotta.py
flottaauto_h4rck4n0-0.1.0.dist-info/METADATA
flottaauto_h4rck4n0-0.1.0.dist-info/WHEEL
flottaauto_h4rck4n0-0.1.0.dist-info/top_level.txt
flottaauto_h4rck4n0-0.1.0.dist-info/RECORD
