Metadata-Version: 2.4
Name: FlottaAuto-h4rck4n0
Version: 0.1.0
Summary: Gestione Flotta Auto - progetto del corso Python di Hacknow - roby7979
Home-page: 
Author: h4rck4n0
Dynamic: author
Dynamic: description
Dynamic: description-content-type
Dynamic: summary
